aws_recommendation_a4/__init__.py
aws_recommendation_a4/cloudwatch.py
aws_recommendation_a4/cost_estimations.py
aws_recommendation_a4/dynamodb.py
aws_recommendation_a4/ebs.py
aws_recommendation_a4/ec2.py
aws_recommendation_a4/elb.py
aws_recommendation_a4/kms.py
aws_recommendation_a4/rds.py
aws_recommendation_a4/recommendation.py
aws_recommendation_a4/redshift.py
aws_recommendation_a4/s3.py
aws_recommendation_a4/truted_advisor.py
aws_recommendation_a4/utils.py
aws_recommendation_a4-0.0.16.dist-info/LICENCE
aws_recommendation_a4-0.0.16.dist-info/METADATA
aws_recommendation_a4-0.0.16.dist-info/WHEEL
aws_recommendation_a4-0.0.16.dist-info/top_level.txt
aws_recommendation_a4-0.0.16.dist-info/RECORD
